annual/__init__.py
annual/datecalc.py
annual/decorators.py
annual/model.py
annual/py.typed
annual/registry.py
annual/ruleparser.py
annual/functions/__init__.py
annual/functions/easter_funcs.py
annual-0.1.3.dist-info/entry_points.txt
annual-0.1.3.dist-info/LICENSE
annual-0.1.3.dist-info/WHEEL
annual-0.1.3.dist-info/METADATA
annual-0.1.3.dist-info/RECORD
