Metadata-Version: 2.1
Name: annual
Version: 0.1.3
Summary: comment goes here.
Author-email: tom65536 <peregrinus@planet.ms>
Requires-Python: >=3.11
Classifier: License :: OSI Approved :: MIT License
Classifier: Development Status :: 2 - Pre-Alpha
Classifier: Intended Audience :: Developers
Classifier: Intended Audience :: Education
Classifier: Programming Language :: Python :: 3.11
Classifier: Programming Language :: Python :: 3.12
Classifier: Programming Language :: Python :: 3.13
Classifier: Typing :: Typed
Requires-Dist: lark~=1.1
Requires-Dist: build ~= 1.2 ; extra == "build"
Project-URL: Home, https://github.com/tom65536/annual
Project-URL: Source, https://github.com/tom65536/annual
Provides-Extra: build
